[

  
   {
    "id": "firewall-basics",
    "title": "Understanding Network Firewalls",
    "date": "2025-10-25",
    "excerpt": "Learn how firewalls protect your systems and data from modern cyber threats.",
    "content": "Firewalls are essential for protecting your network from unauthorized access and cyber threats...",
    "image": "assets/img/blog-firewall.jpg",
    "link": "blogs/firewall-basics.html"
  },
 {
    "id": "cyber-impact",
    "title": "Impact of Cybersecurity Knowledge in Today's Society",
    "date": "2025-10-31",
    "excerpt": "Explore how cybersecurity awareness is shaping modern digital culture, protecting lives and economies.",
    "content": "Cybersecurity knowledge empowers individuals, businesses, and governments to detect, prevent, and respond to online threats...",
    "image": "assets/img/blog-cyberimpact.jpg",
    "link": "blogs/cyber-impact.html"
  }

]
